fuckjpeg/__init__.py
fuckjpeg/__main__.py
fuckjpeg-0.0.4.dist-info/entry_points.txt
fuckjpeg-0.0.4.dist-info/LICENSE
fuckjpeg-0.0.4.dist-info/WHEEL
fuckjpeg-0.0.4.dist-info/METADATA
fuckjpeg-0.0.4.dist-info/RECORD
