Metadata-Version: 2.1
Name: fuckjpeg
Version: 0.0.4
Summary: Renames .jpeg files to .jpg because I really don't like that file extension. 
Keywords: rename,filename,images,image,jpeg,jpg
Author-email: James Hodgkinson <james@terminaloutcomes.com>
Classifier: License :: OSI Approved :: MIT License
Requires-Dist: click >=8.0.1
Requires-Dist: pytest ; extra == "dev"
Requires-Dist: mypy ; extra == "dev"
Requires-Dist: flit ; extra == "dev"
Project-URL: Home, https://github.com/yaleman/fuckjpeg
Provides-Extra: dev
